inabox.py
inabox-0.5.10.dist-info/LICENSE
inabox-0.5.10.dist-info/METADATA
inabox-0.5.10.dist-info/WHEEL
inabox-0.5.10.dist-info/entry_points.txt
inabox-0.5.10.dist-info/RECORD
