Metadata-Version: 2.1
Name: inabox
Version: 0.5.10
Summary: Knowit Automation lifecycle management
Home-page: https://inabox.openknowit.com
License: MIT
Author: Jakob Holst
Author-email: jakob.holst@knowit.dk
Requires-Python: >=3.8,<4.0
Classifier: License :: OSI Approved :: MIT License
Classifier: Programming Language :: Python :: 3
Classifier: Programming Language :: Python :: 3.8
Classifier: Programming Language :: Python :: 3.9
Classifier: Programming Language :: Python :: 3.10
Classifier: Programming Language :: Python :: 3.11
Requires-Dist: requests (>=2.25,<3.0)
Project-URL: Repository, https://github.com/miracle-as/openknowit_inabox.git
